LICENSE.txt
MANIFEST.in
README.txt
setup.cfg
setup.py
docs/HISTORY.txt
pleiades/__init__.py
pleiades.transliteration.egg-info/PKG-INFO
pleiades.transliteration.egg-info/SOURCES.txt
pleiades.transliteration.egg-info/dependency_links.txt
pleiades.transliteration.egg-info/entry_points.txt
pleiades.transliteration.egg-info/namespace_packages.txt
pleiades.transliteration.egg-info/not-zip-safe
pleiades.transliteration.egg-info/requires.txt
pleiades.transliteration.egg-info/top_level.txt
pleiades/transliteration/__init__.py
pleiades/transliteration/ws_copt.py
pleiades/transliteration/ws_en.py
pleiades/transliteration/ws_grek.py
pleiades/transliteration/ws_latn.py
pleiades/transliteration/ws_tr.py