Metadata-Version: 1.0
Name: pleiades.transliteration
Version: 0.5
Summary: Transliteration of names from various writing systems to our modern Roman writing system following conventions of the Pleiades Project.
Home-page: UNKNOWN
Author: Tom Elliot
Author-email: tom.elliott@nyu.edu
License: BSD
Keywords: ancient language greek latin transliteration
Platform: UNKNOWN
Classifier: Programming Language :: Python
Classifier: Topic :: Software Development :: Libraries :: Python Modules
